cartolidar/__init__.py
cartolidar/__main__.py
cartolidar/_version.py
cartolidar/qlidtwins.py
cartolidar/clidax/__init__.py
cartolidar/clidax/clidaux.py
cartolidar/clidax/clidcarto.py
cartolidar/clidax/clidconfig.py
cartolidar/clidax/clidraster.py
cartolidar/clidfr/__init__.py
cartolidar/clidfr/cliddata.py
cartolidar/clidfr/clidhead.py
cartolidar/clidtools/__init__.py
cartolidar/clidtools/__main__.py
cartolidar/clidtools/clidtwcfg.py
cartolidar/clidtools/clidtwinb.py
cartolidar/clidtools/clidtwinp.py
cartolidar/clidtools/clidtwins.py
cartolidar/clidtools/clidtwinx.py
cartolidar/data/asc/PuenteDuero/348_4600_2017_alt95.asc
cartolidar/data/asc/PuenteDuero/348_4600_2017_cob050_200cm.asc
cartolidar/data/asc/PuenteDuero/348_4600_2017_fcc3m.asc
cartolidar/data/asc/PuenteDuero/348_4600_2017_fcc5m.asc
cartolidar/data/asc/PuenteDuero/348_4602_2017_alt95.asc
cartolidar/data/asc/PuenteDuero/348_4602_2017_cob050_200cm.asc
cartolidar/data/asc/PuenteDuero/348_4602_2017_fcc3m.asc
cartolidar/data/asc/PuenteDuero/348_4602_2017_fcc5m.asc
cartolidar/data/asc/Riaza/454_4576_2017_Alt95.asc
cartolidar/data/asc/Riaza/454_4576_2017_Fcc5m.asc
cartolidar/data/ext/io/LandCover.csv
cartolidar/data/ext/io/VLRs.geo
cartolidar/data/ext/io/VLRs_20220303.geo
cartolidar/data/ext/io/VLRs_20220709.geo
cartolidar/data/ext/io/VLRs_Old.geo
cartolidar/data/ext/io/classificationLookup.csv
cartolidar/data/ext/io/lasEPSG25830.geo
cartolidar/data/ext/io/lasEPSG25830.wkt
cartolidar/data/ext/io/lasHeadFields.cfg
cartolidar/data/ext/io/lasHeadVlr.cfg
cartolidar/data/ext/io/lasPointFields.cfg
cartolidar/data/ext/io/listaBloquesSelec.cfg
cartolidar/data/ext/io/reClasificador.csv
cartolidar/data/mfe/PuenteDuero/MFE_PuenteDuero.dbf
cartolidar/data/mfe/PuenteDuero/MFE_PuenteDuero.prj
cartolidar/data/mfe/PuenteDuero/MFE_PuenteDuero.shp
cartolidar/data/mfe/PuenteDuero/MFE_PuenteDuero.shx
cartolidar/data/mfe/Riaza/MFE_Riaza.dbf
cartolidar/data/mfe/Riaza/MFE_Riaza.prj
cartolidar/data/mfe/Riaza/MFE_Riaza.shp
cartolidar-0.0a14.dist-info/LICENSE
cartolidar-0.0a14.dist-info/METADATA
cartolidar-0.0a14.dist-info/WHEEL
cartolidar-0.0a14.dist-info/top_level.txt
cartolidar-0.0a14.dist-info/RECORD
