Metadata-Version: 2.1
Name: cartolidar
Version: 0.0a14
Summary: Lidar data processing tools focused on Spanish PNOA datasets
Home-page: https://github.com/cartolid/cartolidar
Author: Jose Bengoa
Author-email: cartolidar@gmail.com
License: GNU GPLv3
Project-URL: Source, https://github.com/cartolid/cartolidar
Project-URL: Bug Reports, https://github.com/cartolid/cartolidar/issues
Project-URL: PNOA Lidar data, https://centrodedescargas.cnig.es
Keywords: lidar,forestry,dasometry,dasoLidar,DLV,PNOA,GIS,DEM,DTM,DSM
Classifier: Development Status :: 3 - Alpha
Classifier: Environment :: Console
Classifier: Intended Audience :: End Users/Desktop
Classifier: License :: OSI Approved :: GNU General Public License v3 (GPLv3)
Classifier: Natural Language :: Spanish
Classifier: Natural Language :: English
Classifier: Operating System :: Microsoft :: Windows
Classifier: Operating System :: POSIX :: Linux
Classifier: Programming Language :: Python :: 3.7
Classifier: Topic :: Scientific/Engineering :: GIS
Requires-Python: >=3.7
License-File: LICENSE
Requires-Dist: gdal (>=3.0.2)
Requires-Dist: numpy (>=1.19.1)
Requires-Dist: scipy (>=1.4.1)
Requires-Dist: psutil (>=5.7.0)
Requires-Dist: dbfread (>=2.0.7)
Requires-Dist: pytest (>=7.1.2)
Requires-Dist: numba (==0.53.0)
